angel/__init__.py
angel/alg/__init__.py
angel/alg/iAngel.py
angel/alg/iArchAngel.py
angelcommunity-2.0.0.dist-info/LICENSE
angelcommunity-2.0.0.dist-info/METADATA
angelcommunity-2.0.0.dist-info/WHEEL
angelcommunity-2.0.0.dist-info/top_level.txt
angelcommunity-2.0.0.dist-info/RECORD
