Metadata-Version: 2.1
Name: angelcommunity
Version: 2.0.0
Summary: Community Discovery algorithm
Home-page: https://github.com/GiulioRossetti/ANGEL
Author: Giulio Rossetti
Author-email: giulio.rossetti@gmail.com
License: BSD-2-Clause
Keywords: complex-networks,community discovery
Classifier: Development Status :: 5 - Production/Stable
Classifier: Intended Audience :: Developers
Classifier: Topic :: Software Development :: Build Tools
Classifier: License :: OSI Approved :: BSD License
Classifier: Operating System :: OS Independent
Classifier: Programming Language :: Python
Classifier: Programming Language :: Python :: 3
License-File: LICENSE
